autorandr.py
autorandr-1.14.post1.dist-info/METADATA
autorandr-1.14.post1.dist-info/WHEEL
autorandr-1.14.post1.dist-info/entry_points.txt
autorandr-1.14.post1.dist-info/top_level.txt
autorandr-1.14.post1.dist-info/RECORD
