Metadata-Version: 2.1
Name: autorandr
Version: 1.14.post1
Summary: Automatically select a display configuration based on connected devices
Home-page: https://github.com/phillipberndt/autorandr
Author: Phillip Berndt
Author-email: phillip.berndt@googlemail.com
License: GPLv3
Keywords: xrandr
Platform: UNKNOWN
Classifier: Environment :: Console
Classifier: Intended Audience :: End Users/Desktop
Classifier: License :: OSI Approved :: GNU General Public License v3 (GPLv3)
Classifier: Programming Language :: Python :: 2
Classifier: Programming Language :: Python :: 2.7
Classifier: Programming Language :: Python :: 3
Classifier: Programming Language :: Python :: 3.3
Classifier: Programming Language :: Python :: 3.4
Classifier: Programming Language :: Python :: 3.6
Classifier: Programming Language :: Python :: 3.7
Classifier: Programming Language :: Python :: 3.8
Classifier: Programming Language :: Python :: 3.9
Classifier: Programming Language :: Python :: 3.10
